PyQt5/Qt/lib/libQt5WebEngine.so.5
PyQt5/Qt/lib/libQt5WebEngineCore.so.5
PyQt5/Qt/lib/libQt5WebEngineWidgets.so.5
PyQt5/Qt/libexec/QtWebEngineProcess
PyQt5/Qt/libexec/qt.conf
PyQt5/Qt/qml/QtWebEngine/libqtwebengineplugin.so
PyQt5/Qt/qml/QtWebEngine/plugins.qmltypes
PyQt5/Qt/qml/QtWebEngine/qmldir
PyQt5/Qt/qml/QtWebEngine/Controls1Delegates/AlertDialog.qml
PyQt5/Qt/qml/QtWebEngine/Controls1Delegates/AuthenticationDialog.qml
PyQt5/Qt/qml/QtWebEngine/Controls1Delegates/ColorDialog.qml
PyQt5/Qt/qml/QtWebEngine/Controls1Delegates/ConfirmDialog.qml
PyQt5/Qt/qml/QtWebEngine/Controls1Delegates/FilePicker.qml
PyQt5/Qt/qml/QtWebEngine/Controls1Delegates/Menu.qml
PyQt5/Qt/qml/QtWebEngine/Controls1Delegates/MenuItem.qml
PyQt5/Qt/qml/QtWebEngine/Controls1Delegates/MenuSeparator.qml
PyQt5/Qt/qml/QtWebEngine/Controls1Delegates/PromptDialog.qml
PyQt5/Qt/qml/QtWebEngine/Controls1Delegates/ToolTip.qml
PyQt5/Qt/qml/QtWebEngine/Controls1Delegates/TouchHandle.qml
PyQt5/Qt/qml/QtWebEngine/Controls1Delegates/TouchSelectionMenu.qml
PyQt5/Qt/qml/QtWebEngine/Controls1Delegates/qmldir
PyQt5/Qt/qml/QtWebEngine/Controls2Delegates/AlertDialog.qml
PyQt5/Qt/qml/QtWebEngine/Controls2Delegates/AuthenticationDialog.qml
PyQt5/Qt/qml/QtWebEngine/Controls2Delegates/ConfirmDialog.qml
PyQt5/Qt/qml/QtWebEngine/Controls2Delegates/Menu.qml
PyQt5/Qt/qml/QtWebEngine/Controls2Delegates/MenuItem.qml
PyQt5/Qt/qml/QtWebEngine/Controls2Delegates/MenuSeparator.qml
PyQt5/Qt/qml/QtWebEngine/Controls2Delegates/PromptDialog.qml
PyQt5/Qt/qml/QtWebEngine/Controls2Delegates/ToolTip.qml
PyQt5/Qt/qml/QtWebEngine/Controls2Delegates/information.png
PyQt5/Qt/qml/QtWebEngine/Controls2Delegates/qmldir
PyQt5/Qt/qml/QtWebEngine/Controls2Delegates/question.png
PyQt5/Qt/resources/icudtl.dat
PyQt5/Qt/resources/qtwebengine_devtools_resources.pak
PyQt5/Qt/resources/qtwebengine_resources.pak
PyQt5/Qt/resources/qtwebengine_resources_100p.pak
PyQt5/Qt/resources/qtwebengine_resources_200p.pak
PyQt5/Qt/translations/qtwebengine_ca.qm
PyQtWebEngine_Qt-5.15.2.dist-info/LICENSE
PyQtWebEngine_Qt-5.15.2.dist-info/METADATA
PyQtWebEngine_Qt-5.15.2.dist-info/WHEEL
PyQtWebEngine_Qt-5.15.2.dist-info/RECORD
